LICENSE
README.md
pyproject.toml
setup.py
src/base92/__init__.py
src/base92/_base92compiled.pyi
src/base92/_base92extension.c
src/base92/_base92python.py
src/base92.egg-info/PKG-INFO
src/base92.egg-info/SOURCES.txt
src/base92.egg-info/dependency_links.txt
src/base92.egg-info/top_level.txt
tests/test_chr_ord.py
tests/test_exhaustive.py
tests/test_integration.py
tests/test_unit.py