Metadata-Version: 2.4
Name: base92
Version: 2.0.0
Summary: A library to create base92 encoded strings.
Author-email: thenoviceoof <thenoviceoof@gmail.com>
License-Expression: MIT
Project-URL: Repository, https://github.com/thenoviceoof/base92
Project-URL: Issues, https://github.com/thenoviceoof/base92/issues
Classifier: Programming Language :: Python :: 3
Classifier: Operating System :: OS Independent
Requires-Python: >3.0
License-File: LICENSE
Dynamic: license-file
